fase/__init__.py
fase/cli/__init__.py
fase/cli/main.py
fase/cli/templates/alembic.ini
fase/cli/templates/env.py
fase/cli/templates/init.py
fase/cli/templates/script.py.mako
fase/core/__init__.py
fase/core/app.py
fase/core/config.py
fase/core/curd.py
fase/core/db.py
fase/logging.py
fase/main.py
fase/singletone.py
fase-0.1.0.dist-info/METADATA
fase-0.1.0.dist-info/WHEEL
fase-0.1.0.dist-info/RECORD
