Metadata-Version: 2.1
Name: fase
Version: 0.1.0
Summary: 
Author: SmsS4
Author-email: smss.lite@gmail.com
Requires-Python: >=3.8,<4.0
Classifier: Programming Language :: Python :: 3
Classifier: Programming Language :: Python :: 3.8
Classifier: Programming Language :: Python :: 3.9
Classifier: Programming Language :: Python :: 3.10
Classifier: Programming Language :: Python :: 3.11
Classifier: Programming Language :: Python :: 3.12
Requires-Dist: dynaconf (>=3.2.5,<4.0.0)
Requires-Dist: fastapi (>=0.110.0,<0.111.0)
Requires-Dist: sqlalchemy (>=2.0.29,<3.0.0)
Requires-Dist: uvicorn (>=0.29.0,<0.30.0)
